textract_analysis/__init__.py
textract_analysis/textract_functions.py
textract_analysis-0.1.2.dist-info/METADATA
textract_analysis-0.1.2.dist-info/WHEEL
textract_analysis-0.1.2.dist-info/top_level.txt
textract_analysis-0.1.2.dist-info/RECORD
