Metadata-Version: 2.1
Name: textract-analysis
Version: 0.1.2
Summary: A package for analyzing ID documents using AWS Textract
Author: Swarup
Author-email: swarup.ogma@gmail.com
Classifier: Programming Language :: Python :: 3
Classifier: License :: OSI Approved :: MIT License
Classifier: Operating System :: OS Independent
Requires-Python: >=3.6
Requires-Dist: boto3
